{
  "transfer_id": "t_20260322_002",
  "file_id": "f_11fe9156",
  "filename": "test-upload.txt",
  "requester": "SolanaLeeky",
  "issue_number": 17,
  "started_at": "2026-03-22T08:45:09.663937+00:00",
  "status": "in_progress",
  "total_chunks": 1,
  "received_chunks": 0,
  "failed_chunks": 0,
  "timeout_at": "2026-03-22T08:55:09.663937+00:00",
  "chunks": {
    "chunk_000": {
      "status": "pending",
      "assigned_peer": "SolanaLeeky/peer-node-01",
      "from": "",
      "at": ""
    }
  }
}
